BBDown_GUI/BBDown.exe
BBDown_GUI/__init__.py
BBDown_GUI/__main__.py
BBDown_GUI/aria2c.exe
BBDown_GUI/ffmpeg.exe
BBDown_GUI/gui.py
BBDown_GUI/tool.py
BBDown_GUI/Form/form_about.py
BBDown_GUI/Form/form_login.py
BBDown_GUI/Form/form_main.py
BBDown_GUI/Form/form_output.py
BBDown_GUI/UI/favicon.ico
BBDown_GUI/UI/ui_about.py
BBDown_GUI/UI/ui_main.py
BBDown_GUI/UI/ui_output.py
BBDown_GUI/UI/ui_qrcode.py
BBDown_GUI-1.1.0.2.dist-info/LICENSE
BBDown_GUI-1.1.0.2.dist-info/METADATA
BBDown_GUI-1.1.0.2.dist-info/WHEEL
BBDown_GUI-1.1.0.2.dist-info/entry_points.txt
BBDown_GUI-1.1.0.2.dist-info/top_level.txt
BBDown_GUI-1.1.0.2.dist-info/RECORD
