Metadata-Version: 2.1
Name: BBDown-GUI
Version: 1.1.0.2
Summary: BBDown using the graphical interface.
Home-page: https://github.com/1299172402/BBDown_GUI
Author: 之雨
License: MIT
Keywords: gui,bbdown,bilibili,download
Classifier: License :: OSI Approved :: MIT License
Classifier: Programming Language :: Python
Classifier: Programming Language :: Python :: 3
Classifier: Operating System :: Microsoft :: Windows
Requires-Python: >=3.6
License-File: LICENSE
Requires-Dist: PyQt5 (==5.15.6)
